[
    {
        "id": "17754860156497",
        "reservation_id": "17754857142246",
        "user_email": "ax@gmail.com",
        "user_nom": "amine",
        "activity_id": 2,
        "activity_nom": "Sortie en bateau",
        "creneau": "demi-journee",
        "nb_personnes": 3,
        "message": "",
        "statut": "planifiee",
        "date_creation": "2026-04-06 16:33:35"
    },
    {
        "id": "17755142886759",
        "reservation_id": "17755142116884",
        "user_email": "Aze@gmail.com",
        "user_nom": "amine",
        "activity_id": 1,
        "activity_nom": "Plong\u00e9e sous-marine",
        "creneau": "demi-journee",
        "nb_personnes": 1,
        "message": "",
        "statut": "en_attente",
        "date_creation": "2026-04-07 00:24:48"
    },
    {
        "id": "17755143861002",
        "reservation_id": "17755142116884",
        "user_email": "Aze@gmail.com",
        "user_nom": "amine",
        "activity_id": 2,
        "activity_nom": "Sortie en bateau",
        "creneau": "demi-journee",
        "nb_personnes": 4,
        "message": "",
        "statut": "planifiee",
        "date_creation": "2026-04-07 00:26:26"
    },
    {
        "id": "17755153459698",
        "reservation_id": "17755152569537",
        "user_email": "za@gmail.com",
        "user_nom": "az",
        "activity_id": 1,
        "activity_nom": "Plong\u00e9e sous-marine",
        "creneau": "demi-journee",
        "nb_personnes": 2,
        "message": "",
        "statut": "planifiee",
        "date_creation": "2026-04-07 00:42:25"
    },
    {
        "id": "17755153859722",
        "reservation_id": "17755152569537",
        "user_email": "za@gmail.com",
        "user_nom": "az",
        "activity_id": 1,
        "activity_nom": "Plong\u00e9e sous-marine",
        "creneau": "demi-journee",
        "nb_personnes": 3,
        "message": "",
        "statut": "planifiee",
        "date_creation": "2026-04-07 00:43:05"
    },
    {
        "id": "17755505278385",
        "reservation_id": "17755504376295",
        "user_email": "hdiuhc@gmail.com",
        "user_nom": "ifoizkzsh",
        "activity_id": 1,
        "activity_nom": "Plong\u00e9e sous-marine",
        "creneau": "demi-journee",
        "nb_personnes": 3,
        "message": "",
        "statut": "en_attente",
        "date_creation": "2026-04-07 10:28:47"
    }
]